{
  "0": "agradecimento",
  "1": "alcool_seguro_coracao",
  "2": "avisos_medicamento",
  "3": "cansaco_falta_de_ar_oque_fazer",
  "4": "clinicas_proximas",
  "5": "colesterol_alto_perigoso_coracao",
  "6": "compartilhar_com_medico",
  "7": "controlar_estresse_proteger_coracao",
  "8": "dados_saude_coletados",
  "9": "danos_doencas_cardiacas",
  "10": "diabetes_risco_doencas_cardiacas",
  "11": "dietas_saudaveis",
  "12": "dificuldade_respirar_insuficiencia_cardiaca",
  "13": "doenca_angina",
  "14": "doenca_cardiomiopatia",
  "15": "doenca_hipertensao",
  "16": "dor_no_peito_causas",
  "17": "dor_no_peito_serio",
  "18": "efeitos_doencas_cardiacas",
  "19": "estresse_afeta_saude",
  "20": "exame_ecg",
  "21": "exames_detecta_doencas_cardiacas",
  "22": "exames_sangue",
  "23": "exercicios_coracao",
  "24": "exercicios_protegem_coracao",
  "25": "falta_de_ar_doenca_cardiaca",
  "26": "fatores_risco_doencas_cardiacas",
  "27": "finalizacao_conversa",
  "28": "fumar_afeta_coracao",
  "29": "habitos_para_melhorar_saude",
  "30": "insuficiencia_cardiaca_inchaco",
  "31": "melhor_dieta_coracao",
  "32": "monitorar_pressao",
  "33": "niveis_colesterol",
  "34": "o_que_e_arritmia_cardiaca",
  "35": "palpitacoes_significado",
  "36": "pressao_alta_problemas_coracao",
  "37": "prevenir_doencas_cardiacas",
  "38": "recomendacoes_autocuidado",
  "39": "risco_de_ter_doencas_cardiacas",
  "40": "riscos_doencas_cardiacas",
  "41": "saudacao",
  "42": "segunda_opiniao_medica",
  "43": "seguranca_informacoes_saude",
  "44": "sinais_alerta_infarto_miocardio",
  "45": "sinais_sintomas_doencas_cardiacas",
  "46": "sintomas_infarto",
  "47": "sintomas_insuficiencia_cardiaca",
  "48": "sugerir_diagnostico",
  "49": "tontura_problemas_cardiacos",
  "50": "tratamentos_arritmias_cardiacas"
}